[
	{
		"__TYPE__": "SharedSliceContent",
		"variation": "projectLegend",
		"primary": {},
		"items": [
			{
				"__TYPE__": "GroupItemContent",
				"value": [
					[
						"legend_title",
						{
							"__TYPE__": "StructuredTextContent",
							"value": [
								{
									"type": "heading3",
									"content": {
										"text": "Typical"
									}
								}
							]
						}
					],
					[
						"legend_description",
						{
							"__TYPE__": "StructuredTextContent",
							"value": [
								{
									"type": "paragraph",
									"content": {
										"text": "Laborum qui amet amet irure laborum commodo culpa velit eu cillum nulla. Lorem qui id quis proident elit mollit consectetur id sunt elit ad. Do ad consectetur incididunt exercitation id sint."
									}
								}
							]
						}
					]
				]
			}
		]
	},
	{
		"__TYPE__": "SharedSliceContent",
		"variation": "projectDescription",
		"primary": {},
		"items": [
			{
				"__TYPE__": "GroupItemContent",
				"value": [
					[
						"project_subtitle",
						{
							"__TYPE__": "StructuredTextContent",
							"value": [
								{
									"type": "heading2",
									"content": {
										"text": "Package"
									}
								}
							]
						}
					],
					[
						"paragraph",
						{
							"__TYPE__": "StructuredTextContent",
							"value": [
								{
									"type": "paragraph",
									"content": {
										"text": "Consectetur ad eiusmod laborum pariatur duis. Magna Lorem culpa veniam ex dolore deserunt duis."
									}
								}
							]
						}
					]
				]
			}
		]
	},
	{
		"__TYPE__": "SharedSliceContent",
		"variation": "projectImages",
		"primary": {},
		"items": [
			{
				"__TYPE__": "GroupItemContent",
				"value": [
					[
						"image_gallery",
						{
							"origin": {
								"id": "main",
								"url": "https://images.unsplash.com/photo-1607582278043-57198ac8da43",
								"width": 4024,
								"height": 4024
							},
							"url": "https://images.unsplash.com/photo-1607582278043-57198ac8da43?rect=0%2C0%2C4024%2C4024&w=500&h=500",
							"width": 500,
							"height": 500,
							"edit": {
								"zoom": 1,
								"crop": {
									"x": 0,
									"y": 0
								},
								"background": "transparent"
							},
							"credits": null,
							"alt": null,
							"__TYPE__": "ImageContent",
							"thumbnails": {}
						}
					]
				]
			}
		]
	},
	{
		"__TYPE__": "SharedSliceContent",
		"variation": "default",
		"primary": {
			"project_title": {
				"__TYPE__": "StructuredTextContent",
				"value": [
					{
						"type": "heading1",
						"content": {
							"text": "Shall"
						}
					}
				]
			},
			"project_index": {
				"__TYPE__": "StructuredTextContent",
				"value": [
					{
						"type": "paragraph",
						"content": {
							"text": "01",
							"spans": []
						},
						"direction": "ltr"
					}
				]
			},
			"hero_image": {
				"origin": {
					"id": "main",
					"url": "https://images.unsplash.com/photo-1606248897732-2c5ffe759c04",
					"width": 4000,
					"height": 4000
				},
				"url": "https://images.unsplash.com/photo-1606248897732-2c5ffe759c04",
				"width": 4000,
				"height": 4000,
				"edit": {
					"zoom": 1,
					"crop": {
						"x": 0,
						"y": 0
					},
					"background": "transparent"
				},
				"credits": null,
				"alt": null,
				"__TYPE__": "ImageContent",
				"thumbnails": {}
			},
			"project_brief": {
				"__TYPE__": "StructuredTextContent",
				"value": [
					{
						"type": "paragraph",
						"content": {
							"text": "Occaecat velit laboris minim aliqua."
						}
					}
				]
			}
		},
		"items": [
			{
				"__TYPE__": "GroupItemContent",
				"value": []
			}
		]
	}
]